stackit/sqlserverflex/__init__.py
stackit/sqlserverflex/api/__init__.py
stackit/sqlserverflex/api/default_api.py
stackit/sqlserverflex/api_client.py
stackit/sqlserverflex/api_response.py
stackit/sqlserverflex/configuration.py
stackit/sqlserverflex/exceptions.py
stackit/sqlserverflex/models/__init__.py
stackit/sqlserverflex/models/acl.py
stackit/sqlserverflex/models/backup.py
stackit/sqlserverflex/models/backup_list_backups_response_grouped.py
stackit/sqlserverflex/models/create_database_payload.py
stackit/sqlserverflex/models/create_database_response.py
stackit/sqlserverflex/models/create_instance_payload.py
stackit/sqlserverflex/models/create_instance_response.py
stackit/sqlserverflex/models/create_user_payload.py
stackit/sqlserverflex/models/create_user_response.py
stackit/sqlserverflex/models/data_point.py
stackit/sqlserverflex/models/database.py
stackit/sqlserverflex/models/database_documentation_create_database_request_options.py
stackit/sqlserverflex/models/database_options.py
stackit/sqlserverflex/models/flavor.py
stackit/sqlserverflex/models/get_backup_response.py
stackit/sqlserverflex/models/get_database_response.py
stackit/sqlserverflex/models/get_instance_response.py
stackit/sqlserverflex/models/get_user_response.py
stackit/sqlserverflex/models/host.py
stackit/sqlserverflex/models/host_metric.py
stackit/sqlserverflex/models/instance.py
stackit/sqlserverflex/models/instance_documentation_acl.py
stackit/sqlserverflex/models/instance_documentation_options.py
stackit/sqlserverflex/models/instance_documentation_storage.py
stackit/sqlserverflex/models/instance_error.py
stackit/sqlserverflex/models/instance_flavor_entry.py
stackit/sqlserverflex/models/instance_list_instance.py
stackit/sqlserverflex/models/instance_list_user.py
stackit/sqlserverflex/models/list_backups_response.py
stackit/sqlserverflex/models/list_collations_response.py
stackit/sqlserverflex/models/list_compatibility_response.py
stackit/sqlserverflex/models/list_databases_response.py
stackit_sqlserverflex-1.1.1.dist-info/METADATA
stackit_sqlserverflex-1.1.1.dist-info/WHEEL
stackit_sqlserverflex-1.1.1.dist-info/licenses/LICENSE.md
stackit_sqlserverflex-1.1.1.dist-info/licenses/NOTICE.txt
stackit_sqlserverflex-1.1.1.dist-info/RECORD
